debparse/__init__.py
debparse/api.py
debparse/utils.py
debparse-0.1.1.dist-info/DESCRIPTION.rst
debparse-0.1.1.dist-info/METADATA
debparse-0.1.1.dist-info/metadata.json
debparse-0.1.1.dist-info/RECORD
debparse-0.1.1.dist-info/top_level.txt
debparse-0.1.1.dist-info/WHEEL
